{"witnesses": [{"id": "Le1", "tokens": [{"t": "VIIII"}, {"t": "INDECOLUM"}, {"t": "AD"}, {"t": "ALIUM"}, {"t": "REGEM"}, {"t": "CUM"}, {"t": "LEGATIO"}, {"t": "DIREGITUR"}, {"t": "ET"}, {"t": "UERBIS"}, {"t": "SUGGERIT"}, {"t": "COMMENDATIUM"}, {"t": "domino"}, {"t": "glorioso"}, {"t": "atque"}, {"t": "praecellentissimo"}, {"t": "fratri"}, {"t": "illo"}, {"t": "regi"}, {"t": "in"}, {"t": "dei"}, {"t": "nomen"}, {"t": "ille"}, {"t": "rex"}, {"t": "desideratus"}, {"t": "euentus"}, {"t": "fidelissima"}, {"t": "nobis"}, {"t": "obtulit"}, {"t": "facultatem"}, {"t": "qua"}, {"t": "uestrae"}, {"t": "serenitatem"}, {"t": "salutationis"}, {"t": "honorificenciam"}, {"t": "praebeamus"}, {"t": "eo"}, {"t": "uidelicet"}, {"t": "dileccionis"}, {"t": "affectu"}, {"t": "proprietatem"}, {"t": "uestrae"}, {"t": "celsitudinis"}, {"t": "cognuscire"}, {"t": "cupientes"}, {"t": "quo"}, {"t": "uestram"}, {"t": "gloriam"}, {"t": "erga"}, {"t": "nos"}, {"t": "fraternitatis"}, {"t": "indiuiduam"}, {"t": "arbitramur"}, {"t": "proinde"}, {"t": "praesentes"}, {"t": "uiros"}, {"t": "inlustris"}, {"t": "illos"}, {"t": "et"}, {"t": "illos"}, {"t": "ad"}, {"t": "praesenciam"}, {"t": "fraternitatis"}, {"t": "uestre"}, {"t": "direximus"}, {"t": "quibus"}, {"t": "ut"}, {"t": "uestram"}, {"t": "gloriam"}, {"t": "condecit"}, {"t": "benignissima"}, {"t": "tranquillitatae"}, {"t": "susceptis"}, {"t": "petimus"}, {"t": "ut"}, {"t": "dum"}, {"t": "officium"}, {"t": "legacionis"}, {"t": "iniunctae"}, {"t": "peraegerint"}, {"t": "responsis"}, {"t": "uestrae"}, {"t": "clemencia"}, {"t": "premuniti"}, {"t": "ad"}, {"t": "referendum"}, {"t": "salutis"}, {"t": "indicium"}, {"t": "sacris"}, {"t": "uestris"}, {"t": "litteris"}, {"t": "honorentur"}]}, {"id": "Le3", "tokens": [{"t": "EPISTULA"}, {"t": "REGALIS"}, {"t": "AD"}, {"t": "ALIUM"}, {"t": "REGE"}, {"t": "DESTINENDA"}, {"t": "domino"}, {"t": "glorioso"}, {"t": "atque"}, {"t": "praecellentissimo"}, {"t": "fratri"}, {"t": "illo"}, {"t": "regi"}, {"t": "ego"}, {"t": "in"}, {"t": "dei"}, {"t": "nomine"}, {"t": "ille"}, {"t": "gratia"}, {"t": "dei"}, {"t": "rex"}, {"t": "desideratus"}, {"t": "euentus"}, {"t": "fidelissimam"}, {"t": "nobis"}, {"t": "obtulit"}, {"t": "facultatem"}, {"t": "qua"}, {"t": "uestrae"}, {"t": "serenitatis"}, {"t": "salutationis"}, {"t": "honorificentiam"}, {"t": "praebeamus"}, {"t": "eo"}, {"t": "uidelicet"}, {"t": "dilectionis"}, {"t": "affectu"}, {"t": "prosperitatem"}, {"t": "uestrae"}, {"t": "celsitudinis"}, {"t": "cognoscere"}, {"t": "cupientes"}, {"t": "quo"}, {"t": "uestrae"}, {"t": "fraternitatis"}, {"t": "gloriam"}, {"t": "erga"}, {"t": "nos"}, {"t": "indiuiduam"}, {"t": "arbitramur"}, {"t": "proinde"}, {"t": "presentes"}, {"t": "uiros"}, {"t": "illustres"}, {"t": "illos"}, {"t": "uel"}, {"t": "illos"}, {"t": "ad"}, {"t": "praesentiae"}, {"t": "fraternitatis"}, {"t": "uestrae"}, {"t": "direximus"}, {"t": "quibus"}, {"t": "ut"}, {"t": "uestrae"}, {"t": "dignitati"}, {"t": "condecet"}, {"t": "benignissima"}, {"t": "tranquillitate"}, {"t": "susceptis"}, {"t": "petimus"}, {"t": "ut"}, {"t": "dum"}, {"t": "officium"}, {"t": "legationis"}, {"t": "iniuncte"}, {"t": "peregerint"}, {"t": "responsis"}, {"t": "uestrae"}, {"t": "clementiae"}, {"t": "praemoniti"}, {"t": "ad"}, {"t": "referendum"}, {"t": "salutis"}, {"t": "indicium"}, {"t": "sacris"}, {"t": "litteris"}, {"t": "exaretur"}, {"t": "ualete"}]}, {"id": "P12", "tokens": [{"t": "VIIII"}, {"t": "INDICULUM"}, {"t": "AD"}, {"t": "ALIUM"}, {"t": "REGEM"}, {"t": "CUM"}, {"t": "LEGATIO"}, {"t": "DIRIGITUR"}, {"t": "ET"}, {"t": "UERBIS"}, {"t": "SUGGERIT"}, {"t": "COMMENDATICIIS"}, {"t": "domino"}, {"t": "glorioso"}, {"t": "atque"}, {"t": "praecellentissimo"}, {"t": "fratri"}, {"t": "illo"}, {"t": "regi"}, {"t": "in"}, {"t": "dei"}, {"t": "nomen"}, {"t": "ille"}, {"t": "rex"}, {"t": "desideratus"}, {"t": "euentus"}, {"t": "fidelissimam"}, {"t": "nobis"}, {"t": "obtulit"}, {"t": "facultatem"}, {"t": "quia"}, {"t": "uestrae"}, {"t": "serenitate"}, {"t": "salutationis"}, {"t": "honorificentiuam"}, {"t": "praebeamus"}, {"t": "eo"}, {"t": "uidelicet"}, {"t": "dilectiones"}, {"t": "affectu"}, {"t": "proprietate"}, {"t": "uestrae"}, {"t": "celsitudinis"}, {"t": "cognoscere"}, {"t": "cupientes"}, {"t": "quo"}, {"t": "uestram"}, {"t": "gloriam"}, {"t": "erga"}, {"t": "nos"}, {"t": "fraternitatis"}, {"t": "indiuiduam"}, {"t": "arbitramur"}, {"t": "proinde"}, {"t": "praesentes"}, {"t": "uiros"}, {"t": "inlustris"}, {"t": "illos"}, {"t": "et"}, {"t": "illos"}, {"t": "ad"}, {"t": "praesentiam"}, {"t": "fraternitatis"}, {"t": "uestrae"}, {"t": "direximus"}, {"t": "quibus"}, {"t": "uestram"}, {"t": "gloriam"}, {"t": "condecet"}, {"t": "benignissimam"}, {"t": "tranquillitate"}, {"t": "susceptis"}, {"t": "petimus"}, {"t": "ut"}, {"t": "dum"}, {"t": "officium"}, {"t": "legacionis"}, {"t": "iniuncte"}, {"t": "peregerent"}, {"t": "responsis"}, {"t": "uestrae"}, {"t": "clementiae"}, {"t": "praemoniti"}, {"t": "ad"}, {"t": "referendum"}, {"t": "salutis"}, {"t": "indicium"}, {"t": "sacris"}, {"t": "uestris"}, {"t": "litteris"}, {"t": "honorentur"}]}, {"id": "P16a", "tokens": [{"t": "VIIII"}, {"t": "INDICOLUM"}, {"t": "AD"}, {"t": "ALIUM"}, {"t": "REGEM"}, {"t": "CUM"}, {"t": "LEG[...]"}, {"t": "[...]TUR"}, {"t": "ET"}, {"t": "UERBIS"}, {"t": "SUGERIT"}, {"t": "COMMENDATICIUM"}, {"t": "domino"}, {"t": "glorioso"}, {"t": "atque"}, {"t": "praecellentissimo"}, {"t": "fratre"}, {"t": "illo"}, {"t": "rege"}, {"t": "in"}, {"t": "dei"}, {"t": "nomen"}, {"t": "illi"}, {"t": "rex"}, {"t": "desideratus"}, {"t": "euentus"}, {"t": "fidissimam"}, {"t": "nobis"}, {"t": "obtulit"}, {"t": "facultatem"}, {"t": "qua"}, {"t": "uestrae"}, {"t": "serenitate"}, {"t": "salutacionis"}, {"t": "honorificenciam"}, {"t": "praebeamus"}, {"t": "eo"}, {"t": "uidelicet"}, {"t": "dileccionis"}, {"t": "affectu"}, {"t": "prosperitati"}, {"t": "uestre"}, {"t": "celsitudinis"}, {"t": "cognuscere"}, {"t": "cupientes"}, {"t": "quo"}, {"t": "uestram"}, {"t": "gloriam"}, {"t": "erga"}, {"t": "nus"}, {"t": "fraternitatis"}, {"t": "indiuiduam"}, {"t": "arbitramur"}, {"t": "proinde"}, {"t": "praesentes"}, {"t": "uiris"}, {"t": "inlustres"}, {"t": "illos"}, {"t": "et"}, {"t": "illos"}, {"t": "ad"}, {"t": "praesenciam"}, {"t": "fraternitatis"}, {"t": "uestre"}, {"t": "direximus"}, {"t": "quibus"}, {"t": "ut"}, {"t": "uestra"}, {"t": "gloria"}, {"t": "condecet"}, {"t": "benignissima"}, {"t": "tranquillitate"}, {"t": "susceptis"}, {"t": "petimus"}, {"t": "ut"}, {"t": "dum"}, {"t": "officium"}, {"t": "legacionis"}, {"t": "iniuncte"}, {"t": "peregerint"}, {"t": "responsis"}, {"t": "uestre"}, {"t": "clemenciae"}, {"t": "praemuniti"}, {"t": "ad"}, {"t": "referendum"}, {"t": "salutis"}, {"t": "indicium"}, {"t": "sacris"}, {"t": "uestris"}, {"t": "litteris"}, {"t": "honorentur"}]}, {"id": "P3", "tokens": [{"t": "[fol.132vb]"}, {"t": "LIIII"}, {"t": "IN"}, {"t": "DICULU[M]"}, {"t": "AD"}, {"t": "ALIU[M]"}, {"t": "REGEM"}, {"t": "CUM"}, {"t": "LIGATIO"}, {"t": "DIRIGITUR"}, {"t": "ET"}, {"t": "UERBIS"}, {"t": "SUGGERIT"}, {"t": "CMD"}, {"t": "domino"}, {"t": "glorioso"}, {"t": "atque"}, {"t": "praecelentissimo"}, {"t": "fratri"}, {"t": "illo"}, {"t": "regi"}, {"t": "in"}, {"t": "dei"}, {"t": "nomen"}, {"t": "ille"}, {"t": "rex"}, {"t": "desideratus"}, {"t": "euentus"}, {"t": "fidelissimam"}, {"t": "nobis"}, {"t": "obtullit"}, {"t": "facultatem"}, {"t": "quanta"}, {"t": "nobis"}, {"t": "serenitas"}, {"t": "salutationis"}, {"t": "honorificentiam"}, {"t": "praebeamus"}, {"t": "eo"}, {"t": "uidelicet"}, {"t": "dileccionis"}, {"t": "affectu"}, {"t": "prosperitate"}, {"t": "uestre"}, {"t": "celsitudinis"}, {"t": "cognuscere"}, {"t": "cupientes"}, {"t": "quo"}, {"t": "nostre"}, {"t": "gloriae"}, {"t": "erga"}, {"t": "nos"}, {"t": "fraternitas"}, {"t": "indiuiduam"}, {"t": "arbitramur"}, {"t": "proinde"}, {"t": "praesentis"}, {"t": "uiris"}, {"t": "inlustris"}, {"t": "illo"}, {"t": "et"}, {"t": "illo"}, {"t": "ad"}, {"t": "praesentiam"}, {"t": "fraternitatis"}, {"t": "uestre"}, {"t": "direximus"}, {"t": "quibus"}, {"t": "ut"}, {"t": "uestram"}, {"t": "gloriam"}, {"t": "decet"}, {"t": "benignissima"}, {"t": "tranquillitate"}, {"t": "susceptis"}, {"t": "petimus"}, {"t": "ut"}, {"t": "dum"}, {"t": "officium"}, {"t": "legacionis"}, {"t": "peregerint"}, {"t": "responsionis"}, {"t": "uestre"}, {"t": "clementiae"}, {"t": "praemuniti"}, {"t": "ad"}, {"t": "referendum"}, {"t": "salutis"}, {"t": "inditium"}, {"t": "sacris"}, {"t": "uestris"}, {"t": "literis"}, {"t": "honorentur"}]}, {"id": "Udd", "tokens": [{"t": "IX"}, {"t": "INDECOLUM"}, {"t": "AD"}, {"t": "ALIUM"}, {"t": "REGEM"}, {"t": "CUM"}, {"t": "LIGATIO"}, {"t": "DIREGITUR"}, {"t": "ET"}, {"t": "UERBIS"}, {"t": "SUGERIT"}, {"t": "COMMENDATIUM"}, {"t": "domino"}, {"t": "glorioso"}, {"t": "atque"}, {"t": "precellentissimo"}, {"t": "fratre"}, {"t": "illo"}, {"t": "rege"}, {"t": "in"}, {"t": "dei"}, {"t": "nomen"}, {"t": "illi"}, {"t": "rex"}, {"t": "desideratus"}, {"t": "euentus"}, {"t": "fidelissima"}, {"t": "nobis"}, {"t": "obtullit"}, {"t": "facultatem"}, {"t": "qua"}, {"t": "uestrae"}, {"t": "serenitatem"}, {"t": "salutacionis"}, {"t": "honorificenciam"}, {"t": "prebeamus"}, {"t": "eo"}, {"t": "uidelicet"}, {"t": "dilecciones"}, {"t": "affectu"}, {"t": "prosperitate"}, {"t": "uestre"}, {"t": "celsitudinis"}, {"t": "cognuscire"}, {"t": "cupientes"}, {"t": "quo"}, {"t": "uestram"}, {"t": "gloriam"}, {"t": "erga"}, {"t": "nus"}, {"t": "fraternitatis"}, {"t": "indiuiduam"}, {"t": "arbitramur"}, {"t": "proinde"}, {"t": "presentes"}, {"t": "uiros"}, {"t": "inlustris"}, {"t": "illo"}, {"t": "et"}, {"t": "illo"}, {"t": "ad"}, {"t": "presenciam"}, {"t": "fraternitatis"}, {"t": "uestre"}, {"t": "direximus"}, {"t": "quibus"}, {"t": "ut"}, {"t": "uestra"}, {"t": "gloria"}, {"t": "condecit"}, {"t": "benignissima"}, {"t": "tranquillitatae"}, {"t": "susceptis"}, {"t": "petimus"}, {"t": "ut"}, {"t": "dum"}, {"t": "officium"}, {"t": "legacionis"}, {"t": "iniuncte"}, {"t": "peraegerint"}, {"t": "responsis"}, {"t": "uestre"}, {"t": "clemenciae"}, {"t": "premoniti"}, {"t": "ad"}, {"t": "referendum"}, {"t": "salutis"}, {"t": "inditium"}, {"t": "sacris"}, {"t": "uestris"}, {"t": "literis"}, {"t": "honorentur"}]}, {"id": "Zeu", "tokens": [{"t": "9"}, {"t": "indecolum"}, {"t": "ad"}, {"t": "alium"}, {"t": "regem"}, {"t": "cum"}, {"t": "legatio"}, {"t": "diregitur"}, {"t": "et"}, {"t": "uerbis"}, {"t": "suggerit"}, {"t": "commendatium"}, {"t": "domino"}, {"t": "glorioso"}, {"t": "atque"}, {"t": "precellentissimo"}, {"t": "fratri"}, {"t": "illo"}, {"t": "regi"}, {"t": "in"}, {"t": "dei"}, {"t": "nomen"}, {"t": "ille"}, {"t": "rex"}, {"t": "desideratus"}, {"t": "euentus"}, {"t": "fidelissima"}, {"t": "nobis"}, {"t": "obtulit"}, {"t": "facultatem"}, {"t": "qua"}, {"t": "uestrae"}, {"t": "serenitatem"}, {"t": "salutationis"}, {"t": "honorificenciam"}, {"t": "prebeamus"}, {"t": "eo"}, {"t": "uidelicet"}, {"t": "dileccionis"}, {"t": "affectu"}, {"t": "prosperitatem"}, {"t": "uestrae"}, {"t": "celsitudinis"}, {"t": "cognuscire"}, {"t": "cupientes"}, {"t": "quo"}, {"t": "uestram"}, {"t": "gloriam"}, {"t": "erga"}, {"t": "nos"}, {"t": "fraternitatis"}, {"t": "indiuiduam"}, {"t": "arbitramur"}, {"t": "proinde"}, {"t": "presentes"}, {"t": "uiros"}, {"t": "inlustris"}, {"t": "illos"}, {"t": "et"}, {"t": "illos"}, {"t": "ad"}, {"t": "presenciam"}, {"t": "fraternitatis"}, {"t": "uestre"}, {"t": "direximus"}, {"t": "quibus"}, {"t": "ut"}, {"t": "uestram"}, {"t": "gloriam"}, {"t": "condecit"}, {"t": "benignissima"}, {"t": "tranquillitatae"}, {"t": "susceptis"}, {"t": "petimus"}, {"t": "ut"}, {"t": "dum"}, {"t": "officium"}, {"t": "legacionis"}, {"t": "iniunctae"}, {"t": "peraegerint"}, {"t": "responsis"}, {"t": "uestrae"}, {"t": "clemenciae"}, {"t": "premuniti"}, {"t": "ad"}, {"t": "referendum"}, {"t": "salutis"}, {"t": "indicium"}, {"t": "sacris"}, {"t": "uestris"}, {"t": "litteris"}, {"t": "honorentur"}]}]}